GRANDE/GRANDE.py
GRANDE/__init__.py
GRANDE-0.1.6.dist-info/LICENSE
GRANDE-0.1.6.dist-info/METADATA
GRANDE-0.1.6.dist-info/WHEEL
GRANDE-0.1.6.dist-info/top_level.txt
GRANDE-0.1.6.dist-info/RECORD
