Metadata-Version: 2.1
Name: GRANDE
Version: 0.1.6
Summary: A novel ensemble method for hard, axis-aligned decision trees learned end-to-end with gradient descent.
Home-page: https://github.com/s-marton/GRANDE
Author: Sascha Marton
Author-email: sascha.marton@gmail.com
License: MIT
License-File: LICENSE
Requires-Dist: category-encoders ==2.6.1
Requires-Dist: pandas >=2.0.3
Requires-Dist: tensorflow ==2.16.1
Requires-Dist: numpy >=1.24.3
Requires-Dist: scikit-learn >=1.3.0
Requires-Dist: focal-loss ==0.0.7
